epic_expreval/__init__.py
epic_expreval/evalctx.py
epic_expreval/functions.py
epic_expreval/tokenizer.py
epic_expreval-0.1.0.dist-info/licenses/LICENSE
epic_expreval-0.1.0.dist-info/METADATA
epic_expreval-0.1.0.dist-info/WHEEL
epic_expreval-0.1.0.dist-info/top_level.txt
epic_expreval-0.1.0.dist-info/RECORD
