Metadata-Version: 2.4
Name: epic-expreval
Version: 0.1.0
Summary: Unreal Engine expression evaluator written in Python
Author-email: Paweł Lidwin <linguin@tutanota.com>
License: MIT
Project-URL: homepage, https://github.com/imLinguin/epic-expreval
Project-URL: issues, https://github.com/imLinguin/epic-expreval/issues
Project-URL: repository, https://github.com/imLinguin/epic-expreval.git
Keywords: epic games,unreal engine,legendary-gl
Classifier: Development Status :: 4 - Beta
Classifier: License :: OSI Approved :: MIT License
Classifier: Programming Language :: Python :: 3
Classifier: Programming Language :: Python :: 3.9
Requires-Python: >=3.9
License-File: LICENSE
Requires-Dist: psutil>=7.0.0
Dynamic: license-file
